README.rst
setup.py
multithreaddecorator/__init__.py
multithreaddecorator.egg-info/PKG-INFO
multithreaddecorator.egg-info/SOURCES.txt
multithreaddecorator.egg-info/dependency_links.txt
multithreaddecorator.egg-info/top_level.txt