Metadata-Version: 1.0
Name: multithreaddecorator
Version: 0.0.1
Summary: UNKNOWN
Home-page: UNKNOWN
Author: Dmitriy Shikhalev
Author-email: dmitriy.shikhalev@gmail.com
License: UNKNOWN
Platform: UNKNOWN
